try3code/__init__.py
try3code/loader.py
try3code/data/A1.txt
try3code/data/A2.txt
try3code/data/A3.txt
try3code/data/A4.txt
try3code/data/A5.txt
try3code/data/B1.txt
try3code/data/B2.txt
try3code/data/B4.txt
try3code/data/B6.txt
try3code/data/B7.txt
try3code/data/DL.txt
try3code-1.1.dist-info/METADATA
try3code-1.1.dist-info/WHEEL
try3code-1.1.dist-info/top_level.txt
try3code-1.1.dist-info/RECORD
