Metadata-Version: 2.1
Name: try3code
Version: 1.1
Summary: A custom code reader from text files
Author: Your Name
